copilot_helper.py
dbt_copilot_helper/COMMANDS.md
dbt_copilot_helper/README.md
dbt_copilot_helper/__init__.py
dbt_copilot_helper/addon-plans.yml
dbt_copilot_helper/addons-template-map.yml
dbt_copilot_helper/commands/__init__.py
dbt_copilot_helper/commands/application.py
dbt_copilot_helper/commands/bootstrap.py
dbt_copilot_helper/commands/check_cloudformation.py
dbt_copilot_helper/commands/codebase.py
dbt_copilot_helper/commands/conduit.py
dbt_copilot_helper/commands/config.py
dbt_copilot_helper/commands/copilot.py
dbt_copilot_helper/commands/dns.py
dbt_copilot_helper/commands/environment.py
dbt_copilot_helper/commands/generate.py
dbt_copilot_helper/commands/pipeline.py
dbt_copilot_helper/custom_resources/__init__.py
dbt_copilot_helper/custom_resources/s3_object.py
dbt_copilot_helper/default-addons.yml
dbt_copilot_helper/exceptions.py
dbt_copilot_helper/jinja2_tags.py
dbt_copilot_helper/templates/.copilot/config.yml
dbt_copilot_helper/templates/.copilot/image_build_run.sh
dbt_copilot_helper/templates/.copilot/phases/build.sh
dbt_copilot_helper/templates/.copilot/phases/install.sh
dbt_copilot_helper/templates/.copilot/phases/post_build.sh
dbt_copilot_helper/templates/.copilot/phases/pre_build.sh
dbt_copilot_helper/templates/COMMANDS.md.jinja
dbt_copilot_helper/templates/addon-instructions.txt
dbt_copilot_helper/templates/addons/README.md
dbt_copilot_helper/templates/addons/env/addons.parameters.yml
dbt_copilot_helper/templates/addons/env/aurora-postgres.yml
dbt_copilot_helper/templates/addons/env/monitoring.yml
dbt_copilot_helper/templates/addons/env/opensearch.yml
dbt_copilot_helper/templates/addons/env/rds-postgres.yml
dbt_copilot_helper/templates/addons/env/redis-cluster.yml
dbt_copilot_helper/templates/addons/env/s3.yml
dbt_copilot_helper/templates/addons/env/vpc.yml
dbt_copilot_helper/templates/addons/svc/appconfig-ipfilter.yml
dbt_copilot_helper/templates/addons/svc/s3-policy.yml
dbt_copilot_helper/templates/addons/svc/subscription-filter.yml
dbt_copilot_tools-5.0.3.dist-info/LICENSE
dbt_copilot_tools-5.0.3.dist-info/METADATA
dbt_copilot_tools-5.0.3.dist-info/WHEEL
dbt_copilot_tools-5.0.3.dist-info/entry_points.txt
dbt_copilot_tools-5.0.3.dist-info/RECORD
