Metadata-Version: 2.1
Name: dbt-copilot-tools
Version: 5.0.3
Summary: Set of tools to help transfer applications/services from GOV.UK PaaS to DBT PaaS augmenting AWS Copilot.
License: MIT
Author: Department for Business and Trade Platform Team
Author-email: sre-team@digital.trade.gov.uk
Requires-Python: >=3.9,<4.0
Classifier: License :: OSI Approved :: MIT License
Classifier: Programming Language :: Python :: 3
Classifier: Programming Language :: Python :: 3.9
Classifier: Programming Language :: Python :: 3.10
Classifier: Programming Language :: Python :: 3.11
Classifier: Programming Language :: Python :: 3.12
Requires-Dist: Jinja2 (>=3.1.3,<4.0.0)
Requires-Dist: PyYAML (==6.0.1)
Requires-Dist: aiohttp (>=3.8.4,<4.0.0)
Requires-Dist: boto3 (>=1.28.24,<2.0.0)
Requires-Dist: boto3-stubs (>=1.26.148,<2.0.0)
Requires-Dist: botocore (>=1.29.31,<2.0.0)
Requires-Dist: certifi (>=2023.07.22,<2024.0.0)
Requires-Dist: cfn-flip (==1.3.0)
Requires-Dist: cfn-lint (>=0.80.2,<0.81.0)
Requires-Dist: checkov (>=3.1.67,<4.0.0)
Requires-Dist: click (>=8.1.3,<9.0.0)
Requires-Dist: cloudfoundry-client (==1.35.2)
Requires-Dist: cryptography (>=41.0.3,<42.0.0)
Requires-Dist: jinja2-simple-tags (>=0.5.0,<0.6.0)
Requires-Dist: mypy-boto3-codebuild (>=1.26.0.post1,<2.0.0)
Requires-Dist: prettytable (>=3.9.0,<4.0.0)
Requires-Dist: requests (>=2.31.0,<3.0.0)
Requires-Dist: schema (==0.7.5)
Requires-Dist: semver (>=3.0.2,<4.0.0)
Requires-Dist: tomlkit (>=0.12.2,<0.13.0)
